autoformat/__init__.py
autoformat/autoformat.py
autoformat-1.0.0.dist-info/LICENSE
autoformat-1.0.0.dist-info/METADATA
autoformat-1.0.0.dist-info/WHEEL
autoformat-1.0.0.dist-info/top_level.txt
autoformat-1.0.0.dist-info/RECORD
