Metadata-Version: 2.1
Name: autoformat
Version: 1.0.0
Summary: Automatic, range-aware formatting of time-axis labels for timeseries data using matplotlib.
Home-page: https://github.com/danielhogg/autoformat
Author: Daniel Hogg
Author-email: danielhogg@protonmail.com
License: UNKNOWN
Keywords: matplotlib timeseries datetime
Platform: UNKNOWN
Classifier: Development Status :: 3 - Alpha
Classifier: Intended Audience :: Developers
Classifier: Topic :: Software Development :: Build Tools
Classifier: License :: OSI Approved :: MIT License
Classifier: Programming Language :: Python :: 3
Requires-Python: >=3.5, <4
Requires-Dist: numpy
Requires-Dist: matplotlib
